LICENSE
MANIFEST.in
README.md
setup.py
django_favit.egg-info/PKG-INFO
django_favit.egg-info/SOURCES.txt
django_favit.egg-info/dependency_links.txt
django_favit.egg-info/top_level.txt
favit/__init__.py
favit/admin.py
favit/managers.py
favit/models.py
favit/urls.py
favit/views.py
favit/static/favit/css/favorite.css
favit/static/favit/css/css/favorite.css
favit/static/favit/js/favorite.js
favit/templates/favit/button.html
favit/templates/favit/unfave-button.html
favit/templatetags/__init__.py
favit/templatetags/favit_tags.py