Metadata-Version: 1.1
Name: django-favit
Version: 0.4.0
Summary: A simple reusable app for django that makes it easy to deal with faving
Home-page: https://github.com/streema/django-favit
Author: Streema Team
Author-email: devel@streema.com
License: MIT License
Platform: UNKNOWN
Classifier: Environment :: Web Environment
Classifier: Framework :: Django
Classifier: Intended Audience :: Developers
Classifier: License :: OSI Approved :: MIT License
Classifier: Operating System :: OS Independent
Classifier: Programming Language :: Python
Classifier: Programming Language :: Python :: 2.6
Classifier: Programming Language :: Python :: 2.7
Classifier: Topic :: Internet :: WWW/HTTP
Classifier: Topic :: Internet :: WWW/HTTP :: Dynamic Content
